LICENSE
MANIFEST.in
README.rst
setup.py
Bat_man.egg-info/PKG-INFO
Bat_man.egg-info/SOURCES.txt
Bat_man.egg-info/dependency_links.txt
Bat_man.egg-info/entry_points.txt
Bat_man.egg-info/top_level.txt
batman/__init__.py
batman/batch_downloader.py
batman/definitions.py
batman/feedback.py
batman/gtk_batch_downloader.py
batman/options.py
batman/pafy.py
batman/threads.py
batman/codec_interface/__init__.py
batman/codec_interface/aac.py
batman/codec_interface/base_codec.py
batman/codec_interface/ffmpeg_base_codec.py
batman/codec_interface/libflac.py
batman/codec_interface/libmp3lame.py
batman/codec_interface/libtheora.py
batman/codec_interface/libvorbis.py
batman/codec_interface/libx264.py
batman/codec_interface/libx264_aac.py
batman/codec_interface/theora_vorbis.py
batman/codec_interface/utils.py
batman/glade/aboutDialog.glade
batman/glade/batman-logo.png
batman/glade/insertDialog.glade
batman/glade/mainWindow.glade
batman/glade/optionsDialog.glade
batman/locale/pt_BR/LC_MESSAGES/batman.mo