Metadata-Version: 1.1
Name: Bat-man
Version: 0.3.1
Summary: A YouTube batch downloader and converter.
Home-page: http://github.com/ElegantMonkey/Bat-man
Author: ElegantMonkey
Author-email: ramon100.black@gmail.com
License: UNKNOWN
Platform: UNKNOWN
Classifier: Programming Language :: Python
Classifier: Programming Language :: Python :: 3
Classifier: License :: OSI Approved :: GNU General Public License v3 (GPLv3)
Classifier: Operating System :: Microsoft :: Windows
Classifier: Operating System :: POSIX :: Linux
Classifier: Intended Audience :: End Users/Desktop
Classifier: Environment :: X11 Applications :: GTK
Classifier: Development Status :: 2 - Pre-Alpha
